SystemStatus/Core.py
SystemStatus/__init__.py
erispulse_systemstatus-1.0.3.dist-info/entry_points.txt
erispulse_systemstatus-1.0.3.dist-info/WHEEL
erispulse_systemstatus-1.0.3.dist-info/METADATA
erispulse_systemstatus-1.0.3.dist-info/RECORD
