Metadata-Version: 2.4
Name: ErisPulse-SystemStatus
Version: 1.0.3
Summary: 获取系统内存、CPU、硬盘占用
Author-email: ShanFish <your@email.com>
Requires-Python: >=3.8
License-Expression: MIT
Requires-Dist: psutil
Project-URL: homepage, https://github.com/shanfishapp/ErisPulse-SystemStatus
